Metadata-Version: 2.1
Name: sling-mac-universal
Version: 1.1.6.post1
Summary: Sling Binary for Mac (AMD64 & ARM64)
Home-page: https://github.com/slingdata-io/sling-python
Author: Fritz Larco
Author-email: fritz@slingdata.io
License: UNKNOWN
Download-URL: https://github.com/slingdata-io/sling-python/archive/master.zip
Keywords: sling,etl,elt,extract,load
Platform: UNKNOWN
Classifier: Programming Language :: Python :: 3
Classifier: Intended Audience :: Developers
Classifier: Intended Audience :: Education
Classifier: Intended Audience :: Science/Research
Classifier: Operating System :: MacOS
Classifier: Operating System :: Unix
Classifier: Topic :: Utilities
